odoo10_addon_sale_automatic_workflow_validate_purchase_mto-10.0.1.0.2-py3.8-nspkg.pth
odoo/addons/sale_automatic_workflow_validate_purchase_mto/README.rst
odoo/addons/sale_automatic_workflow_validate_purchase_mto/__init__.py
odoo/addons/sale_automatic_workflow_validate_purchase_mto/__manifest__.py
odoo/addons/sale_automatic_workflow_validate_purchase_mto/data/automatic_workflow.xml
odoo/addons/sale_automatic_workflow_validate_purchase_mto/i18n/ca.po
odoo/addons/sale_automatic_workflow_validate_purchase_mto/i18n/es.po
odoo/addons/sale_automatic_workflow_validate_purchase_mto/i18n/sale_automatic_workflow_validate_purchase_mto.pot
odoo/addons/sale_automatic_workflow_validate_purchase_mto/models/__init__.py
odoo/addons/sale_automatic_workflow_validate_purchase_mto/models/automatic_workflow_job.py
odoo/addons/sale_automatic_workflow_validate_purchase_mto/models/sale_workflow_process.py
odoo/addons/sale_automatic_workflow_validate_purchase_mto/readme/CONFIGURE.rst
odoo/addons/sale_automatic_workflow_validate_purchase_mto/readme/CONTRIBUTORS.rst
odoo/addons/sale_automatic_workflow_validate_purchase_mto/readme/DESCRIPTION.rst
odoo/addons/sale_automatic_workflow_validate_purchase_mto/readme/USAGE.rst
odoo/addons/sale_automatic_workflow_validate_purchase_mto/static/description/icon.png
odoo/addons/sale_automatic_workflow_validate_purchase_mto/static/description/index.html
odoo/addons/sale_automatic_workflow_validate_purchase_mto/tests/__init__.py
odoo/addons/sale_automatic_workflow_validate_purchase_mto/tests/test_sale_automatic_workflow.py
odoo/addons/sale_automatic_workflow_validate_purchase_mto/views/sale_workflow_process.xml
odoo10_addon_sale_automatic_workflow_validate_purchase_mto-10.0.1.0.2.dist-info/METADATA
odoo10_addon_sale_automatic_workflow_validate_purchase_mto-10.0.1.0.2.dist-info/WHEEL
odoo10_addon_sale_automatic_workflow_validate_purchase_mto-10.0.1.0.2.dist-info/namespace_packages.txt
odoo10_addon_sale_automatic_workflow_validate_purchase_mto-10.0.1.0.2.dist-info/top_level.txt
odoo10_addon_sale_automatic_workflow_validate_purchase_mto-10.0.1.0.2.dist-info/RECORD
